ard/__init__.py
ard/cbor.py
ard/cjson.py
ard/decode.py
ard/encode.py
ard/exceptions.py
ard/json.py
ard/read.py
ard/types.py
ard/version.py
ard/write.py
ard/yaml.py
ard-0.0.11.data/scripts/ardconv
ard-0.0.11.dist-info/LICENSE
ard-0.0.11.dist-info/METADATA
ard-0.0.11.dist-info/WHEEL
ard-0.0.11.dist-info/top_level.txt
ard-0.0.11.dist-info/RECORD
