Metadata-Version: 2.1
Name: ard
Version: 0.0.11
Summary: Agnostic Raw Data for Python
Home-page: https://github.com/tliron/python-ard
Download-URL: https://github.com/tliron/python-ard/releases
Author: Tal Liron
Author-email: tal.liron@gmail.com
License: Apache License 2.0
Classifier: Development Status :: 4 - Beta
Classifier: Intended Audience :: Developers
Classifier: License :: OSI Approved :: Apache Software License
License-File: LICENSE
Requires-Dist: ruamel.yaml
Requires-Dist: cbor2
